Metadata-Version: 1.0
Name: tphan86-distributions
Version: 0.1.0
Summary: Gaussian and Binomial distributions
Home-page: UNKNOWN
Author: Tuan Phan
Author-email: tuanpa141186@gmail.com
License: UNKNOWN
Platform: UNKNOWN
